core_of_theaisphere/__init__.py
core_of_theaisphere/_version.py
core_of_theaisphere/archive/__init__.py
core_of_theaisphere/archive/tuners.py
core_of_theaisphere/classic_ml/__init__.py
core_of_theaisphere/classic_ml/classification.py
core_of_theaisphere/classic_ml/classification_pipeline.py
core_of_theaisphere/classic_ml/regression.py
core_of_theaisphere/examples/__init__.py
core_of_theaisphere/examples/best_practices.py
core_of_theaisphere/examples/building_mlp.py
core_of_theaisphere/examples/custom_tuner.py
core_of_theaisphere/examples/hyper_tuning.py
core_of_theaisphere/tuning/__init__.py
core_of_theaisphere/tuning/tune.py
core_of_theaisphere/tuning/tuners.py
core_of_theaisphere/tuning/tuners_dup.py
core_of_theaisphere/utils/__init__.py
core_of_theaisphere/utils/build_sequential_mlp.py
core_of_theaisphere/utils/df_utils.py
core_of_theaisphere/utils/ml_utils.py
core_of_theaisphere/visualizations/__init__.py
core_of_theaisphere/visualizations/classic_ml_plots.py
core_of_theaisphere/visualizations/visualize.py
core_of_theaisphere-0.0.4b0.dist-info/LICENSE
core_of_theaisphere-0.0.4b0.dist-info/METADATA
core_of_theaisphere-0.0.4b0.dist-info/WHEEL
core_of_theaisphere-0.0.4b0.dist-info/top_level.txt
core_of_theaisphere-0.0.4b0.dist-info/RECORD
